mogu_sdk/__init__.py
mogu_sdk/auth.py
mogu_sdk/client.py
mogu_sdk/exceptions.py
mogu_sdk/hitl/__init__.py
mogu_sdk/hitl/base.py
mogu_sdk/hitl/models.py
mogu_sdk/hitl/session_manager.py
mogu_sdk/hitl/utils.py
mogu_sdk/models.py
mogu_sdk/resources/__init__.py
mogu_sdk/resources/cost.py
mogu_sdk/resources/wiki.py
mogu_sdk/settings.py
mogu_sdk-0.1.10.dist-info/METADATA
mogu_sdk-0.1.10.dist-info/WHEEL
mogu_sdk-0.1.10.dist-info/licenses/LICENSE
mogu_sdk-0.1.10.dist-info/RECORD
