Metadata-Version: 2.4
Name: mogu-sdk
Version: 0.1.10
Summary: Official Python SDK for Mogu Workflow Management Platform
License: MIT
License-File: LICENSE
Keywords: mogu,workflow,wiki,sdk,api-client
Author: Mogu Team
Author-email: maaaxcic@gmail.com
Requires-Python: >=3.12,<4.0
Classifier: Development Status :: 3 - Alpha
Classifier: Intended Audience :: Developers
Classifier: License :: OSI Approved :: MIT License
Classifier: Programming Language :: Python :: 3
Classifier: Programming Language :: Python :: 3.12
Classifier: Programming Language :: Python :: 3.13
Classifier: Programming Language :: Python :: 3.14
Classifier: Topic :: Software Development :: Libraries :: Python Modules
Requires-Dist: httpx (>=0.28.1,<0.29.0)
Requires-Dist: pydantic (>=2.12.5,<3.0.0)
Requires-Dist: pydantic-settings (>=2.12.0,<3.0.0)
Requires-Dist: python-dotenv (>=1.1.1,<2.0.0)
Project-URL: Documentation, https://mogu-sdk.readthedocs.io
Project-URL: Homepage, https://github.com/yourusername/mogu-sdk
Project-URL: Repository, https://github.com/yourusername/mogu-sdk
